digitalsign_sdk/__init__.py
digitalsign_sdk/digitalsign-sdk.py
digitalsignature_sdk-0.1.0.dist-info/LICENSE
digitalsignature_sdk-0.1.0.dist-info/METADATA
digitalsignature_sdk-0.1.0.dist-info/WHEEL
digitalsignature_sdk-0.1.0.dist-info/top_level.txt
digitalsignature_sdk-0.1.0.dist-info/RECORD
