Metadata-Version: 2.1
Name: digitalsignature_sdk
Version: 0.1.0
Summary: Python SDK for my digital sign Go backend API
Home-page: https://github.com/kavirajkv/SDK-development-training.git
Author: Kaviraj K
Author-email: kavirajk36kv@gmmail.com
Classifier: Programming Language :: Python :: 3
Classifier: License :: OSI Approved :: MIT License
Classifier: Operating System :: OS Independent
License-File: LICENSE
Requires-Dist: requests>=2.25.1
